TaqnyatSms.py
Taqnyat-1.0.0.dist-info/METADATA
Taqnyat-1.0.0.dist-info/WHEEL
Taqnyat-1.0.0.dist-info/top_level.txt
Taqnyat-1.0.0.dist-info/RECORD
