Metadata-Version: 2.1
Name: Taqnyat
Version: 1.0.0
Summary: taqnyat package for python SMS
Home-page: https://github.com/taqnyat/python
Author: Anas Hamarshi
Author-email: dev@taqnyat.sa
License: UNKNOWN
Keywords: taqnyat sms cpaas
Platform: UNKNOWN
Classifier: Programming Language :: Python :: 3
Classifier: License :: OSI Approved :: MIT License
Classifier: Operating System :: OS Independent
